{
  "project": {
    "show": false
  },
  "supervisorEmail": {
	  "useSupervisorEmail": false
  },
  "home": {
    "logged_in_path": "/dashboard"
  },
  "browse": {
    "pageSize" : 27,
    "useInfiniteScroll" : false 
  },
  "states" : [{"value": "draft", "label":"Draft"},
              {"value": "open", "label":"Open"},
              {"value":"assigned", "label":"Assigned"},
              {"value": "completed", "label":"Completed"},
              {"value":"archived", "label":"Archived"}],
  "fullTimeDetail": {
    "description": "**Description:** What is the _impact_ of this opportunity? What kind of _experience_ will someone gain from the work? You can add links to provide [more info](https://www.usa.gov/)\n\n**Title/Series/Grade:** fill in _requirements_ for this position (or _Unclassified Duties_ if there are no specific title or grade requirements)\n\n**Service/Staff Office:**\n\n**Region:**\n\n"
  }
}
